{
    "custom/void": {
        "format": "",
        "on-click": "wofi --show drun",
        "tooltip": false
    },
    "hyprland/workspaces": {
        "disable-scroll": true,
        "all-outputs": true,
        "warp-on-scroll": false,
        "format": "{name}",
        "format-icons": {
            "urgent": "",
            "active": "",
            "default": ""
        }
    },
    "hyprland/window": {
        "format": "{}",
        "max-length": 50,
        "separator": true
    },
    "pulseaudio": {
        "format": "{icon}  {volume}%",
        "format-bluetooth": "{icon} {volume}% {format_source}",
        "format-bluetooth-muted": " {icon}{format_source}",
        "format-muted": " {format_source}",
        "format-source": " {volume}%",
        "format-source-muted": "",
        "format-icons": {
            "headphone": "",
            "hands-free": "",
            "headset": "",
            "phone": "",
            "portable": "",
            "car": "",
            "default": ["", "", ""]
        },
        "on-click": "pavucontrol",
        "padding": 5
    },
    "network": {
        "format-wifi": "  {essid}",
        "format-ethernet": "  ",
        "format-disconnected": "  ",
        "tooltip-format": "{ipaddr}",
        "padding": 5
    },
    "cpu": {
        "format": "  {usage}%",
        "tooltip": true,
        "padding": 5
    },
    "memory": {
        "format": " {}%",
        "tooltip": true,
        "padding": 5
    },
    "temperature": {
        "interval": 10,
        "hwmon-path": "/sys/devices/platform/coretemp.0/hwmon/hwmon4/temp1_input",
        "critical-threshold": 100,
        "format-critical": " {temperatureC}",
        "format": " {temperatureC}°C",
        "padding": 5
    },
    "hyprland/language": {
        "format": "  {}",
        "format-en": "EN",
        "padding": 5
    },
    "battery": {
        "states": {
            "warning": 30,
            "critical": 15
        },
        "format": "{icon} {capacity}%",
        "format-full": "{icon} {capacity}%",
        "format-charging": " {capacity}%",
        "format-plugged": " {capacity}%",
        "format-alt": "{time} {icon}",
        "format-icons": ["", "", "", "", ""],
        "padding": 5
    },
    "battery#bat2": {
        "bat": "BAT2",
        "padding": 5
    },
    "clock": {
        "format": "{:%H:%M | %e %B} ",
        "tooltip-format": "<big>{:%Y %B}</big>\n<tt><small>{calendar}</small></tt>",
        "format-alt": "{:%Y-%m-%d}",
        "padding": 5
    },
    "tray": {
        "spacing": 10,
        "padding": 5
    }
}
